{
  "contratos": [
    {
      "id": 2,
      "codigo": "1234",
      "cliente": "Claro",
      "tipoContrato": "Alocação",
      "status": "Arquivado",
      "dataCadastro": "2022-01-01",
      "dataInicio": "2022-01-01",
      "dataFim": "2023-01-01",
      "descricao": "Alocação",
      "valor": "1.111,22"
    },
    {
      "id": 3,
      "codigo": "344567",
      "cliente": "Vivo",
      "tipoContrato": "Venda",
      "status": "Vigente",
      "dataCadastro": "2023-02-20",
      "dataInicio": "2023-02-20",
      "dataFim": "2023-03-20",
      "descricao": "Contrato de venda referente aos equipamentos da operadora Vivo.",
      "valor": "123.345,01"
    },
    {
      "id": 5,
      "codigo": "2245678",
      "cliente": "Petrobras",
      "tipoContrato": "Alocação",
      "status": "Novo",
      "dataCadastro": "2020-03-02",
      "dataInicio": "2022-08-02",
      "dataFim": "2020-09-14",
      "descricao": "Alocação",
      "valor": "5.123,33"
    }
  ]
}